dbbpy/__init__.py
dbbpy/compile.py
dbbpy/src/main.cpp
dbbpy/src/optimizer.cpp
dbbpy/src/optimizer.hpp
dbbpy/src/option_cleaner.cpp
dbbpy/src/option_cleaner.hpp
dbbpy/src/utils.hpp
dbbpy-0.1.6.dist-info/LICENSE
dbbpy-0.1.6.dist-info/METADATA
dbbpy-0.1.6.dist-info/WHEEL
dbbpy-0.1.6.dist-info/entry_points.txt
dbbpy-0.1.6.dist-info/RECORD
